pweb_ssr/__init__.py
pweb_ssr/pweb_jinja_extend.py
pweb_ssr/pweb_ssr_module.py
pweb_ssr/common/__init__.py
pweb_ssr/common/pweb_jinja_util.py
pweb_ssr/common/pweb_ssr_config.py
pweb_ssr/common/pweb_ssr_html_file.py
pweb_ssr/common/pweb_ssr_init.py
pweb_ssr/common/pweb_ssr_structure.py
pweb_ssr/form/__init__.py
pweb_ssr/form/form_tag_registry.py
pweb_ssr/form/from_input_common.py
pweb_ssr/html/error-message.html
pweb_ssr/html/form-input.html
pweb_ssr/html/form-view.html
pweb_ssr/html/help-message.html
pweb_ssr/html/pagination.html
pweb_ssr/html/sortable-header.html
pweb_ssr/lib/__init__.py
pweb_ssr/lib/jinja_tag_helper.py
pweb_ssr/table/__init__.py
pweb_ssr/table/table_common.py
pweb_ssr/table/table_tag_registry.py
pweb_ssr-0.0.8.dist-info/LICENSE
pweb_ssr-0.0.8.dist-info/METADATA
pweb_ssr-0.0.8.dist-info/WHEEL
pweb_ssr-0.0.8.dist-info/top_level.txt
pweb_ssr-0.0.8.dist-info/RECORD
