Metadata-Version: 2.1
Name: pweb-ssr
Version: 0.0.8
Summary: Server Side Rendered UI, Form, Table Header, Item Per Page, Pagination, Jinja Customization things
Home-page: https://github.com/banglafighter/pweb-ssr
Author: Bangla Fighter
Author-email: banglafighter.com@gmail.com
License: Apache 2.0
Platform: any
Classifier: Intended Audience :: Developers
Classifier: License :: OSI Approved :: Apache Software License
Classifier: Programming Language :: Python
License-File: LICENSE
Requires-Dist: ppy-common
Requires-Dist: pweb-form-rest
Requires-Dist: ppy-jsonyml
